gridparse/__init__.py
gridparse/grid_argument_parser.py
gridparse/utils.py
gridparse-1.5.5.dist-info/licenses/LICENSE
gridparse-1.5.5.dist-info/METADATA
gridparse-1.5.5.dist-info/WHEEL
gridparse-1.5.5.dist-info/top_level.txt
gridparse-1.5.5.dist-info/RECORD
