Metadata-Version: 2.4
Name: gridparse
Version: 1.5.5
Summary: Grid search directly from argparse
Home-page: https://github.com/gchochla/gridparse
Author: Georgios Chochlakis
Author-email: "Georgios (Yiorgos) Chochlakis" <georgioschochlakis@gmail.com>
Maintainer-email: "Georgios (Yiorgos) Chochlakis" <georgioschochlakis@gmail.com>
License: MIT License
Project-URL: Homepage, https://github.com/gchochla/gridparse
Project-URL: Bug Reports, https://github.com/gchochla/gridparse/issues
Project-URL: Source, https://github.com/gchochla/gridparse
Keywords: machine learning,grid search,argparse
Classifier: Development Status :: 3 - Alpha
Classifier: License :: OSI Approved :: MIT License
Classifier: Programming Language :: Python :: 3
Classifier: Programming Language :: Python :: 3.7
Classifier: Programming Language :: Python :: 3.8
Classifier: Programming Language :: Python :: 3.9
Classifier: Programming Language :: Python :: 3.10
Classifier: Programming Language :: Python :: 3.11
Classifier: Programming Language :: Python :: 3 :: Only
Requires-Python: >=3.7
License-File: LICENSE
Requires-Dist: omegaconf
Provides-Extra: dev
Requires-Dist: black; extra == "dev"
Requires-Dist: pytest; extra == "dev"
Dynamic: author
Dynamic: home-page
Dynamic: license-file
